odoo/addons/sale_order_line_price_lock_by_pricelist/README.rst
odoo/addons/sale_order_line_price_lock_by_pricelist/__init__.py
odoo/addons/sale_order_line_price_lock_by_pricelist/__manifest__.py
odoo/addons/sale_order_line_price_lock_by_pricelist/i18n/es.po
odoo/addons/sale_order_line_price_lock_by_pricelist/i18n/sale_order_line_price_lock_by_pricelist.pot
odoo/addons/sale_order_line_price_lock_by_pricelist/models/__init__.py
odoo/addons/sale_order_line_price_lock_by_pricelist/models/product_pricelist.py
odoo/addons/sale_order_line_price_lock_by_pricelist/models/sale_order.py
odoo/addons/sale_order_line_price_lock_by_pricelist/readme/CONFIGURE.md
odoo/addons/sale_order_line_price_lock_by_pricelist/readme/CONTEXT.md
odoo/addons/sale_order_line_price_lock_by_pricelist/readme/CONTRIBUTORS.md
odoo/addons/sale_order_line_price_lock_by_pricelist/readme/DESCRIPTION.md
odoo/addons/sale_order_line_price_lock_by_pricelist/readme/USAGE.md
odoo/addons/sale_order_line_price_lock_by_pricelist/static/description/icon.png
odoo/addons/sale_order_line_price_lock_by_pricelist/static/description/index.html
odoo/addons/sale_order_line_price_lock_by_pricelist/tests/__init__.py
odoo/addons/sale_order_line_price_lock_by_pricelist/tests/test_sale_order_line_price_lock_by_pricelist.py
odoo/addons/sale_order_line_price_lock_by_pricelist/views/product_pricelist_views.xml
odoo/addons/sale_order_line_price_lock_by_pricelist/views/sale_order_views.xml
odoo_addon_sale_order_line_price_lock_by_pricelist-16.0.1.0.1.dist-info/METADATA
odoo_addon_sale_order_line_price_lock_by_pricelist-16.0.1.0.1.dist-info/WHEEL
odoo_addon_sale_order_line_price_lock_by_pricelist-16.0.1.0.1.dist-info/top_level.txt
odoo_addon_sale_order_line_price_lock_by_pricelist-16.0.1.0.1.dist-info/RECORD
