Metadata-Version: 2.1
Name: odoo-addon-sale_order_line_price_lock_by_pricelist
Version: 16.0.1.0.1
Summary: Lock price or discount edition depending on pricelist items
Home-page: https://github.com/OCA/sale-workflow
Author: Moduon, Odoo Community Association (OCA)
Author-email: support@odoo-community.org
License: LGPL-3
Classifier: Programming Language :: Python
Classifier: Framework :: Odoo
Classifier: Framework :: Odoo :: 16.0
Classifier: License :: OSI Approved :: GNU Lesser General Public License v3 (LGPLv3)
Classifier: Development Status :: 3 - Alpha
Requires-Python: >=3.10
Requires-Dist: odoo-addon-base-view-inheritance-extension<16.1dev,>=16.0dev
Requires-Dist: odoo<16.1dev,>=16.0a
